pyvoicecraft/__init__.py
pyvoicecraft/pyvoicecraft.py
pyvoicecraft-1.0.0.dist-info/licenses/LICENSE
pyvoicecraft-1.0.0.dist-info/METADATA
pyvoicecraft-1.0.0.dist-info/WHEEL
pyvoicecraft-1.0.0.dist-info/entry_points.txt
pyvoicecraft-1.0.0.dist-info/top_level.txt
pyvoicecraft-1.0.0.dist-info/RECORD
