Metadata-Version: 2.4
Name: pyvoicecraft
Version: 1.0.0
Summary: Advanced voice processing package with comprehensive TTS and speech recognition capabilities
Home-page: https://github.com/kodukulla-phani-kumar/pyvoicecraft
Author: Kodukulla.Phani Kumar
Author-email: phanikumark715@gmail.com
Project-URL: Bug Reports, https://github.com/kodukulla-phani-kumar/pyvoicecraft/issues
Project-URL: Source, https://github.com/kodukulla-phani-kumar/pyvoicecraft
Project-URL: Documentation, https://github.com/kodukulla-phani-kumar/pyvoicecraft/wiki
Keywords: voice,speech,tts,text-to-speech,speech-recognition,audio,voice-processing
Classifier: Development Status :: 5 - Production/Stable
Classifier: Intended Audience :: Developers
Classifier: License :: OSI Approved :: MIT License
Classifier: Operating System :: OS Independent
Classifier: Programming Language :: Python :: 3
Classifier: Programming Language :: Python :: 3.7
Classifier: Programming Language :: Python :: 3.8
Classifier: Programming Language :: Python :: 3.9
Classifier: Programming Language :: Python :: 3.10
Classifier: Programming Language :: Python :: 3.11
Classifier: Topic :: Multimedia :: Sound/Audio :: Speech
Classifier: Topic :: Software Development :: Libraries :: Python Modules
Requires-Python: >=3.7
License-File: LICENSE
Requires-Dist: pyttsx3>=2.90
Requires-Dist: SpeechRecognition>=3.8.1
Requires-Dist: PyAudio>=0.2.11
Requires-Dist: numpy>=1.19.0
Requires-Dist: scipy>=1.5.0
Provides-Extra: dev
Requires-Dist: pytest>=6.0; extra == "dev"
Requires-Dist: black>=21.0; extra == "dev"
Requires-Dist: flake8>=3.8; extra == "dev"
Dynamic: author
Dynamic: author-email
Dynamic: classifier
Dynamic: description
Dynamic: description-content-type
Dynamic: home-page
Dynamic: keywords
Dynamic: license-file
Dynamic: project-url
Dynamic: provides-extra
Dynamic: requires-dist
Dynamic: requires-python
Dynamic: summary
